{
  "entity.creeper.primed": {
    "replace": true,
    "category": "hostile",
    "sounds": [{ "name": "random/fuse", "volume": 1.0, "pitch": 3.5 }]
  },
  "block.bone_block.place": {
    "replace": true,
    "category": "neutral",
    "sounds": [{ "name": "random/bad_to_the_bone", "volume": 1.0 }]
  },
  "block.bone_block.break": {
    "replace": true,
    "category": "neutral",
    "sounds": [{ "name": "random/bad_to_the_bone", "volume": 1.0 }]
  },
  "block.bone_block.hit": {
    "replace": true,
    "category": "neutral",
    "sounds": [{ "name": "random/bad_to_the_bone", "volume": 1.0 }]
  },
  "block.bone_block.fall": {
    "replace": true,
    "category": "neutral",
    "sounds": [{ "name": "random/bad_to_the_bone", "volume": 1.0 }]
  },
  "block.bone_block.step": {
    "replace": true,
    "category": "neutral",
    "sounds": [{ "name": "random/bad_to_the_bone", "volume": 1.0 }]
  },
  "entity.skeleton.hurt": {
    "replace": true,
    "category": "hostile",
    "sounds": [{ "name": "random/bad_to_the_bone", "volume": 1.0 }]
  },
  "entity.skeleton.death": {
    "replace": true,
    "category": "hostile",
    "sounds": [{ "name": "random/bad_to_the_bone", "volume": 1.0 }]
  },
  "entity.skeleton.ambient": {
    "replace": true,
    "category": "hostile",
    "sounds": [{ "name": "random/bad_to_the_bone", "volume": 1.0 }]
  },
  "entity.skeleton.shoot": {
    "replace": true,
    "category": "hostile",
    "sounds": [{ "name": "random/bad_to_the_bone", "volume": 1.0 }]
  },
  "entity.skeleton.step": {
    "replace": true,
    "category": "hostile",
    "sounds": [{ "name": "random/bad_to_the_bone", "volume": 1.0 }]
  },
  "entity.skeleton_horse.ambient": {
    "replace": true,
    "category": "neutral",
    "sounds": [{ "name": "random/bad_to_the_bone", "volume": 1.0 }]
  },
  "entity.skeleton_horse.death": {
    "replace": true,
    "category": "neutral",
    "sounds": [{ "name": "random/bad_to_the_bone", "volume": 1.0 }]
  },
  "entity.skeleton_horse.hurt": {
    "replace": true,
    "category": "neutral",
    "sounds": [{ "name": "random/bad_to_the_bone", "volume": 1.0 }]
  },
  "entity.skeleton_horse.step": {
    "replace": true,
    "category": "neutral",
    "sounds": [{ "name": "random/bad_to_the_bone", "volume": 1.0 }]
  },
  "entity.skeleton_horse.swim": {
    "replace": true,
    "category": "neutral",
    "sounds": [{ "name": "random/bad_to_the_bone", "volume": 1.0 }]
  },
  "entity.skeleton_horse.angry": {
    "replace": true,
    "category": "neutral",
    "sounds": [{ "name": "random/bad_to_the_bone", "volume": 1.0 }]
  },
  "entity.skeleton_horse.gallop": {
    "replace": true,
    "category": "neutral",
    "sounds": [{ "name": "random/bad_to_the_bone", "volume": 1.0 }]
  },
  "entity.skeleton_horse.jump": {
    "replace": true,
    "category": "neutral",
    "sounds": [{ "name": "random/bad_to_the_bone", "volume": 1.0 }]
  },
  "entity.skeleton_horse.breathe": {
    "replace": true,
    "category": "neutral",
    "sounds": [{ "name": "random/bad_to_the_bone", "volume": 1.0 }]
  },
  "entity.skeleton_horse.ambient_water": {
    "replace": true,
    "category": "neutral",
    "sounds": [{ "name": "random/bad_to_the_bone", "volume": 1.0 }]
  },
  "entity.skeleton_horse.gallop_water": {
    "replace": true,
    "category": "neutral",
    "sounds": [{ "name": "random/bad_to_the_bone", "volume": 1.0 }]
  },
  "entity.skeleton_horse.jump_water": {
    "replace": true,
    "category": "neutral",
    "sounds": [{ "name": "random/bad_to_the_bone", "volume": 1.0 }]
  },
  "entity.skeleton_horse.step_water": {
    "replace": true,
    "category": "neutral",
    "sounds": [{ "name": "random/bad_to_the_bone", "volume": 1.0 }]
  },
  "entity.villager.celebrate": {
    "replace": true,
    "category": "neutral",
    "sounds": ["mob/villager/yes1", "mob/villager/yes2"]
  },
  "entity.villager.no": {
    "replace": true,
    "category": "neutral",
    "sounds": ["mob/villager/no1", "mob/villager/no2"]
  },
  "entity.villager.hurt": {
    "replace": true,
    "category": "neutral",
    "sounds": ["damage/hit1"]
  },
  "entity.player.hurt": {
    "replace": true,
    "category": "neutral",
    "sounds": ["damage/hit1"]
  },
  "entity.player.death": {
    "replace": true,
    "category": "neutral",
    "sounds": ["damage/death"]
  },
  "entity.creeper.death": {
    "replace": true,
    "category": "hostile",
    "sounds": ["mob/creeper/death"]
  },
  "entity.creeper.hurt": {
    "replace": true,
    "category": "hostile",
    "sounds": ["mob/creeper/hurt"]
  },
  "entity.zombie.hurt": {
    "replace": true,
    "category": "hostile",
    "sounds": ["mob/zombie/hurt"]
  },
  "entity.zombie.death": {
    "replace": true,
    "category": "hostile",
    "sounds": ["mob/zombie/death"]
  },
  "entity.zombie.ambient": {
    "replace": true,
    "category": "hostile",
    "sounds": ["mob/zombie/say1", "mob/zombie/say2", "mob/zombie/say3"]
  },
  "entity.generic.eat": {
    "sounds": ["random/eat"],
    "subtitle": "subtitles.entity.generic.eat",
    "replace": true
  },
  "item.armor.equip_iron": {
    "sounds": [
      {
        "name": "random/metal",
        "pitch": 0.8,
        "weight": 1
      },
      {
        "name": "random/metal",
        "pitch": 0.9,
        "weight": 1
      },
      {
        "name": "random/metal",
        "pitch": 1,
        "weight": 1
      },
      {
        "name": "random/metal",
        "pitch": 1.1,
        "weight": 1
      },
      {
        "name": "random/metal",
        "pitch": 1.2,
        "weight": 1
      },
      {
        "name": "random/metal_comedic_cut1",
        "pitch": 0.8,
        "weight": 1
      },
      {
        "name": "random/metal_comedic_cut1",
        "pitch": 0.9,
        "weight": 1
      },
      {
        "name": "random/metal_comedic_cut1",
        "pitch": 1,
        "weight": 1
      },
      {
        "name": "random/metal_comedic_cut1",
        "pitch": 1.1,
        "weight": 1
      },
      {
        "name": "random/metal_comedic_cut1",
        "pitch": 1.2,
        "weight": 1
      },
      {
        "name": "random/metal_comedic_cut2",
        "pitch": 0.8,
        "weight": 1
      },
      {
        "name": "random/metal_comedic_cut2",
        "pitch": 0.9,
        "weight": 1
      },
      {
        "name": "random/metal_comedic_cut2",
        "pitch": 1,
        "weight": 1
      },
      {
        "name": "random/metal_comedic_cut2",
        "pitch": 1.1,
        "weight": 1
      },
      {
        "name": "random/metal_comedic_cut2",
        "pitch": 1.2,
        "weight": 1
      },
      {
        "name": "random/metal_comedic_cut3",
        "pitch": 0.8,
        "weight": 1
      },
      {
        "name": "random/metal_comedic_cut3",
        "pitch": 0.9,
        "weight": 1
      },
      {
        "name": "random/metal_comedic_cut3",
        "pitch": 1,
        "weight": 1
      },
      {
        "name": "random/metal_comedic_cut3",
        "pitch": 1.1,
        "weight": 1
      },
      {
        "name": "random/metal_comedic_cut3",
        "pitch": 1.2,
        "weight": 1
      }
    ],
    "subtitle": "subtitles.item.armor.equip_iron",
    "replace": true
  },
  "block.iron.place": {
    "sounds": [
      {
        "name": "random/metal",
        "pitch": 0.8,
        "weight": 1
      },
      {
        "name": "random/metal",
        "pitch": 0.9,
        "weight": 1
      },
      {
        "name": "random/metal",
        "pitch": 1,
        "weight": 1
      },
      {
        "name": "random/metal",
        "pitch": 1.1,
        "weight": 1
      },
      {
        "name": "random/metal",
        "pitch": 1.2,
        "weight": 1
      },
      {
        "name": "random/metal_comedic_cut1",
        "pitch": 0.8,
        "weight": 1
      },
      {
        "name": "random/metal_comedic_cut1",
        "pitch": 0.9,
        "weight": 1
      },
      {
        "name": "random/metal_comedic_cut1",
        "pitch": 1,
        "weight": 1
      },
      {
        "name": "random/metal_comedic_cut1",
        "pitch": 1.1,
        "weight": 1
      },
      {
        "name": "random/metal_comedic_cut1",
        "pitch": 1.2,
        "weight": 1
      },
      {
        "name": "random/metal_comedic_cut2",
        "pitch": 0.8,
        "weight": 1
      },
      {
        "name": "random/metal_comedic_cut2",
        "pitch": 0.9,
        "weight": 1
      },
      {
        "name": "random/metal_comedic_cut2",
        "pitch": 1,
        "weight": 1
      },
      {
        "name": "random/metal_comedic_cut2",
        "pitch": 1.1,
        "weight": 1
      },
      {
        "name": "random/metal_comedic_cut2",
        "pitch": 1.2,
        "weight": 1
      },
      {
        "name": "random/metal_comedic_cut3",
        "pitch": 0.8,
        "weight": 1
      },
      {
        "name": "random/metal_comedic_cut3",
        "pitch": 0.9,
        "weight": 1
      },
      {
        "name": "random/metal_comedic_cut3",
        "pitch": 1,
        "weight": 1
      },
      {
        "name": "random/metal_comedic_cut3",
        "pitch": 1.1,
        "weight": 1
      },
      {
        "name": "random/metal_comedic_cut3",
        "pitch": 1.2,
        "weight": 1
      }
    ],
    "replace": true,
    "subtitle": "subtitles.block.generic.place"
  },
  "block.iron.break": {
    "sounds": [
      {
        "name": "random/metal",
        "pitch": 0.6,
        "volume": 1,
        "weight": 1
      },
      {
        "name": "random/metal",
        "pitch": 0.7,
        "volume": 1,
        "weight": 1
      },
      {
        "name": "random/metal",
        "pitch": 0.8,
        "volume": 1,
        "weight": 1
      },
      {
        "name": "random/metal",
        "pitch": 0.9,
        "volume": 1,
        "weight": 1
      }
    ],
    "replace": true,
    "subtitle": "subtitles.block.generic.break"
  },
  "block.iron.hit": {
    "sounds": [
      {
        "name": "random/metal",
        "pitch": 0.6,
        "volume": 0.7,
        "weight": 1
      },
      {
        "name": "random/metal",
        "pitch": 0.7,
        "volume": 0.7,
        "weight": 1
      },
      {
        "name": "random/metal",
        "pitch": 0.8,
        "volume": 0.7,
        "weight": 1
      },
      {
        "name": "random/metal",
        "pitch": 0.9,
        "volume": 0.7,
        "weight": 1
      },
      {
        "name": "random/metal_comedic_cut1",
        "pitch": 0.6,
        "volume": 0.7,
        "weight": 1
      },
      {
        "name": "random/metal_comedic_cut1",
        "pitch": 0.7,
        "volume": 0.7,
        "weight": 1
      },
      {
        "name": "random/metal_comedic_cut1",
        "pitch": 0.8,
        "volume": 0.7,
        "weight": 1
      },
      {
        "name": "random/metal_comedic_cut1",
        "pitch": 0.9,
        "volume": 0.7,
        "weight": 1
      },
      {
        "name": "random/metal_comedic_cut2",
        "pitch": 0.6,
        "volume": 0.7,
        "weight": 1
      },
      {
        "name": "random/metal_comedic_cut2",
        "pitch": 0.7,
        "volume": 0.7,
        "weight": 1
      },
      {
        "name": "random/metal_comedic_cut2",
        "pitch": 0.8,
        "volume": 0.7,
        "weight": 1
      },
      {
        "name": "random/metal_comedic_cut2",
        "pitch": 0.9,
        "volume": 0.7,
        "weight": 1
      },
      {
        "name": "random/metal_comedic_cut3",
        "pitch": 0.6,
        "volume": 0.7,
        "weight": 1
      },
      {
        "name": "random/metal_comedic_cut3",
        "pitch": 0.7,
        "volume": 0.7,
        "weight": 1
      },
      {
        "name": "random/metal_comedic_cut3",
        "pitch": 0.8,
        "volume": 0.7,
        "weight": 1
      },
      {
        "name": "random/metal_comedic_cut3",
        "pitch": 0.9,
        "volume": 0.7,
        "weight": 1
      }
    ],
    "replace": true,
    "subtitle": "subtitles.block.generic.hit"
  },
  "block.iron.step": {
    "sounds": [
      {
        "name": "random/metal",
        "pitch": 0.6,
        "volume": 0.7,
        "weight": 1
      },
      {
        "name": "random/metal",
        "pitch": 0.7,
        "volume": 0.7,
        "weight": 1
      },
      {
        "name": "random/metal",
        "pitch": 0.8,
        "volume": 0.7,
        "weight": 1
      },
      {
        "name": "random/metal",
        "pitch": 0.9,
        "volume": 0.7,
        "weight": 1
      },
      {
        "name": "random/metal_comedic_cut1",
        "pitch": 0.6,
        "volume": 0.7,
        "weight": 1
      },
      {
        "name": "random/metal_comedic_cut1",
        "pitch": 0.7,
        "volume": 0.7,
        "weight": 1
      },
      {
        "name": "random/metal_comedic_cut1",
        "pitch": 0.8,
        "volume": 0.7,
        "weight": 1
      },
      {
        "name": "random/metal_comedic_cut1",
        "pitch": 0.9,
        "volume": 0.7,
        "weight": 1
      },
      {
        "name": "random/metal_comedic_cut2",
        "pitch": 0.6,
        "volume": 0.7,
        "weight": 1
      },
      {
        "name": "random/metal_comedic_cut2",
        "pitch": 0.7,
        "volume": 0.7,
        "weight": 1
      },
      {
        "name": "random/metal_comedic_cut2",
        "pitch": 0.8,
        "volume": 0.7,
        "weight": 1
      },
      {
        "name": "random/metal_comedic_cut2",
        "pitch": 0.9,
        "volume": 0.7,
        "weight": 1
      },
      {
        "name": "random/metal_comedic_cut3",
        "pitch": 0.6,
        "volume": 0.7,
        "weight": 1
      },
      {
        "name": "random/metal_comedic_cut3",
        "pitch": 0.7,
        "volume": 0.7,
        "weight": 1
      },
      {
        "name": "random/metal_comedic_cut3",
        "pitch": 0.8,
        "volume": 0.7,
        "weight": 1
      },
      {
        "name": "random/metal_comedic_cut3",
        "pitch": 0.9,
        "volume": 0.7,
        "weight": 1
      }
    ],
    "replace": true,
    "subtitle": "subtitles.block.generic.footsteps"
  },
  "block.anvil.use": {
    "sounds": [
      {
        "name": "random/metal_but_anvil_use",
        "volume": 2
      }
    ],
    "replace": true,
    "subtitle": "subtitles.block.anvil.use"
  },
  "block.anvil.destroy": {
    "sounds": [
      {
        "name": "random/metal_but_anvil_use",
        "volume": 2
      }
    ],
    "replace": true,
    "subtitle": "subtitles.block.anvil.destroy"
  },
  "block.anvil.break": {
    "sounds": [
      {
        "name": "random/metal_but_really_loud",
        "volume": 2
      }
    ],
    "replace": true,
    "subtitle": "subtitles.block.generic.break"
  },
  "block.anvil.land": {
    "sounds": [
      {
        "name": "random/metal_but_really_loud",
        "volume": 10
      }
    ],
    "replace": true,
    "subtitle": "subtitles.block.anvil.land"
  },
  "block.anvil.place": {
    "sounds": [
      {
        "name": "random/metal_but_really_loud",
        "volume": 2
      }
    ],
    "replace": true,
    "subtitle": "subtitles.block.generic.place"
  },
  "block.water.ambient": {
    "sounds": [
      {
        "name": "liquid/water",
        "weight": 89
      },
      {
        "name": "liquid/water_short",
        "weight": 10
      },
      {
        "name": "liquid/water_long",
        "weight": 1
      }
    ],
    "replace": true,
    "subtitle": "subtitles.block.water.ambient"
  }
}
